{
  "kind": "collectionType",
  "collectionName": "categories",
  "info": {
    "singularName": "category",
    "pluralName": "categories",
    "displayName": "categories"
  },
  "options": {
    "draftAndPublish": true
  },
  "pluginOptions": {},
  "attributes": {
    "name": {
      "type": "string"
    },
    "index": {
      "type": "uid"
    },
    "word": {
      "type": "relation",
      "relation": "manyToOne",
      "target": "api::word.word",
      "inversedBy": "categories"
    }
  }
}
